pyapi_zabbix/__init__.py
pyapi_zabbix/api.py
pyapi_zabbix/logger.py
pyapi_zabbix/sender.py
pyapi_zabbix/version.py
pyapi_zabbix-1.0.0.dist-info/LICENSE
pyapi_zabbix-1.0.0.dist-info/METADATA
pyapi_zabbix-1.0.0.dist-info/WHEEL
pyapi_zabbix-1.0.0.dist-info/top_level.txt
pyapi_zabbix-1.0.0.dist-info/RECORD
