Metadata-Version: 2.1
Name: pyapi-zabbix
Version: 1.0.0
Summary: Python module to work with zabbix.
Home-page: https://github.com/cryol/pyapi-zabbix
Author: Anton Baranov
Author-email: cryol@cryol.kiev.ua
Classifier: Development Status :: 5 - Production/Stable
Classifier: License :: OSI Approved :: GNU General Public License v2 (GPLv2)
Classifier: Programming Language :: Python :: 2
Classifier: Programming Language :: Python :: 3
Classifier: Topic :: System :: Monitoring
Classifier: Topic :: System :: Networking :: Monitoring
Classifier: Topic :: System :: Systems Administration
License-File: LICENSE
